dynatrace/__init__.py
dynatrace/configuration_v1/__init__.py
dynatrace/configuration_v1/alerting_profiles.py
dynatrace/configuration_v1/anomaly_detection_process_groups.py
dynatrace/configuration_v1/api.py
dynatrace/configuration_v1/auto_tags.py
dynatrace/configuration_v1/credential_vault.py
dynatrace/configuration_v1/dashboard.py
dynatrace/configuration_v1/endpoint.py
dynatrace/configuration_v1/extensions.py
dynatrace/configuration_v1/geographic_regions.py
dynatrace/configuration_v1/maintenance_windows.py
dynatrace/configuration_v1/management_zones.py
dynatrace/configuration_v1/metric_events.py
dynatrace/configuration_v1/notifications.py
dynatrace/configuration_v1/oneagent_environment_wide_configuration.py
dynatrace/configuration_v1/oneagent_in_a_hostgroup.py
dynatrace/configuration_v1/oneagent_on_a_host.py
dynatrace/configuration_v1/plugins.py
dynatrace/configuration_v1/schemas.py
dynatrace/configuration_v1/tile.py
dynatrace/dynatrace_object.py
dynatrace/environment_v1/__init__.py
dynatrace/environment_v1/cluster_time.py
dynatrace/environment_v1/custom_device.py
dynatrace/environment_v1/deployment.py
dynatrace/environment_v1/event.py
dynatrace/environment_v1/oneagents.py
dynatrace/environment_v1/smartscape_hosts.py
dynatrace/environment_v1/synthetic_monitors.py
dynatrace/environment_v1/synthetic_third_party.py
dynatrace/environment_v1/timeseries.py
dynatrace/environment_v2/__init__.py
dynatrace/environment_v2/activegates.py
dynatrace/environment_v2/activegates_autoupdate_configuration.py
dynatrace/environment_v2/activegates_autoupdate_jobs.py
dynatrace/environment_v2/audit_logs.py
dynatrace/environment_v2/custom_tags.py
dynatrace/environment_v2/events.py
dynatrace/environment_v2/extensions.py
dynatrace/environment_v2/logs.py
dynatrace/environment_v2/metrics.py
dynatrace/environment_v2/monitored_entities.py
dynatrace/environment_v2/networkzones.py
dynatrace/environment_v2/problems.py
dynatrace/environment_v2/remote_configuration.py
dt-1.2.0.dist-info/METADATA
dt-1.2.0.dist-info/WHEEL
dt-1.2.0.dist-info/licenses/LICENSE
dt-1.2.0.dist-info/RECORD
