Metadata-Version: 2.4
Name: dt
Version: 1.2.0
Summary: Dynatrace API Python client
License-File: LICENSE
Author: David Lopes
Author-email: davidribeirolopes@gmail.com
Maintainer: David Lopes
Maintainer-email: davidribeirolopes@gmail.com
Requires-Python: >=3.6
Classifier: Development Status :: 5 - Production/Stable
Classifier: Intended Audience :: Developers
Classifier: License :: OSI Approved
Classifier: License :: OSI Approved :: Apache Software License
Classifier: Operating System :: MacOS
Classifier: Operating System :: Microsoft :: Windows
Classifier: Operating System :: POSIX :: Linux
Classifier: Programming Language :: Python
Classifier: Programming Language :: Python :: 3
Classifier: Programming Language :: Python :: 3.6
Classifier: Programming Language :: Python :: 3.7
Classifier: Programming Language :: Python :: 3.8
Classifier: Programming Language :: Python :: 3.9
Classifier: Programming Language :: Python :: 3.10
Classifier: Programming Language :: Python :: 3.11
Classifier: Programming Language :: Python :: 3.12
Classifier: Programming Language :: Python :: 3.13
Classifier: Programming Language :: Python :: 3.14
Classifier: Programming Language :: Python :: Implementation :: CPython
Classifier: Topic :: Software Development
Requires-Dist: requests (>=2.22)
Project-URL: Documentation, https://github.com/dynatrace-oss/api-client-python
Project-URL: Homepage, https://github.com/dynatrace-oss/api-client-python
Project-URL: Repository, https://github.com/dynatrace-oss/api-client-python
